ReverseEncodingTree/benchmark/__init__.py
ReverseEncodingTree/benchmark/main_for_mount_everest.py
ReverseEncodingTree/benchmark/main_for_rastrigin.py
ReverseEncodingTree/benchmark/dataset/mount_everest.csv
ReverseEncodingTree/benchmark/dataset/rastrigin.csv
ReverseEncodingTree/benchmark/methods/__init__.py
ReverseEncodingTree/benchmark/methods/evolutor.py
ReverseEncodingTree/benchmark/methods/inherent.py
ReverseEncodingTree/benchmark/methods/obtain_rastrigin.py
ReverseEncodingTree/benchmark/methods/show_me_results.py
ReverseEncodingTree/benchmark/methods/show_ra_results.py
ReverseEncodingTree/configures/example/cart-pole-v0
ReverseEncodingTree/configures/example/lunar-lander-v2
ReverseEncodingTree/configures/example/xor
ReverseEncodingTree/configures/task/cart-pole-v0.bi
ReverseEncodingTree/configures/task/cart-pole-v0.fs
ReverseEncodingTree/configures/task/cart-pole-v0.gs
ReverseEncodingTree/configures/task/cart-pole-v0.n
ReverseEncodingTree/configures/task/logic.bi
ReverseEncodingTree/configures/task/logic.fs
ReverseEncodingTree/configures/task/logic.gs
ReverseEncodingTree/configures/task/logic.n
ReverseEncodingTree/configures/task/lunar-lander-v2.bi
ReverseEncodingTree/configures/task/lunar-lander-v2.fs
ReverseEncodingTree/configures/task/lunar-lander-v2.gs
ReverseEncodingTree/configures/task/lunar-lander-v2.n
ReverseEncodingTree/evolution/__init__.py
ReverseEncodingTree/evolution/evolutor.py
ReverseEncodingTree/evolution/bean/__init__.py
ReverseEncodingTree/evolution/bean/attacker.py
ReverseEncodingTree/evolution/bean/genome.py
ReverseEncodingTree/evolution/bean/species_set.py
ReverseEncodingTree/evolution/methods/__init__.py
ReverseEncodingTree/evolution/methods/bi.py
ReverseEncodingTree/evolution/methods/gs.py
ReverseEncodingTree/example/__init__.py
ReverseEncodingTree/example/cart_pole_v0.py
ReverseEncodingTree/example/cart_pole_v0_with_attacker.py
ReverseEncodingTree/example/lunar_lander_v2.py
ReverseEncodingTree/example/xor.py
ReverseEncodingTree-1.2.2.dist-info/LICENSE
ReverseEncodingTree-1.2.2.dist-info/METADATA
ReverseEncodingTree-1.2.2.dist-info/WHEEL
ReverseEncodingTree-1.2.2.dist-info/top_level.txt
ReverseEncodingTree-1.2.2.dist-info/RECORD
