Metadata-Version: 2.1
Name: ReverseEncodingTree
Version: 1.2.2
Summary: library for the Reverse Encoding Tree
Home-page: https://github.com/HaolingZHANG/ReverseEncodingTree
Author: Haoling Zhang, Chao-Han Huck Yang
Author-email: zhanghaoling@genomics.cn
License: Apache
Keywords: Evolutionary Strategy,NeuroEvolution
Platform: UNKNOWN
Classifier: License :: OSI Approved :: Apache Software License
Classifier: Programming Language :: Python :: 3
Classifier: Operating System :: OS Independent
Requires-Dist: numpy
Requires-Dist: matplotlib
Requires-Dist: graphviz
Requires-Dist: neat-python
Requires-Dist: sklearn
Requires-Dist: gym
Requires-Dist: six
Requires-Dist: pandas
